lsiwh37249_lotto/__init__.py
lsiwh37249_lotto/draw.py
lsiwh37249_lotto-0.2.0.dist-info/METADATA
lsiwh37249_lotto-0.2.0.dist-info/WHEEL
lsiwh37249_lotto-0.2.0.dist-info/top_level.txt
lsiwh37249_lotto-0.2.0.dist-info/RECORD
