Metadata-Version: 2.1
Name: lsiwh37249_lotto
Version: 0.2.0
Summary: Default template for PDM package
Author-email: lsiwh37249 <lsiwh37249@gmail.com>
License: MIT
Requires-Python: >=3.9
